AUTHORS
CHANGELOG.txt
DESCRIPTION
LICENSE
MANIFEST.in
README.rst
setup.py
django_unshorten.egg-info/PKG-INFO
django_unshorten.egg-info/SOURCES.txt
django_unshorten.egg-info/dependency_links.txt
django_unshorten.egg-info/top_level.txt
unshorten/__init__.py
unshorten/admin.py
unshorten/auth.py
unshorten/backend.py
unshorten/decorators.py
unshorten/models.py
unshorten/rate_limit.py
unshorten/urls.py
unshorten/utils.py
unshorten/views.py
unshorten/migrations/0001_initial.py
unshorten/migrations/__init__.py
unshorten/south_migrations/0001_initial.py
unshorten/south_migrations/0002_auto__add_unique_apicalldayhistory_user_creation_date__add_unique_apic.py
unshorten/south_migrations/__init__.py
unshorten/tests/__init__.py
unshorten/tests/models_tests.py
unshorten/tests/rate_limit_tests.py
unshorten/tests/settings.py
unshorten/tests/test_settings.py
unshorten/tests/urls.py
unshorten/tests/views_tests.py