Metadata-Version: 1.0
Name: django-unshorten
Version: 1.0
Summary: A reusable Django app to un-shorten URLs.
